ctgan-enn/__init__.py
ctgan-enn/main.py
ctganenn/__init__.py
ctganenn/main.py
ctganenn-1.0.7.dist-info/METADATA
ctganenn-1.0.7.dist-info/WHEEL
ctganenn-1.0.7.dist-info/top_level.txt
ctganenn-1.0.7.dist-info/RECORD
