Metadata-Version: 2.1
Name: ctganenn
Version: 1.0.7
Summary: CTGAN-ENN : Tabular GAN-based Hybrid sampling method
Home-page: 
Author: Mahayasa Adiputra
Author-email: mahayasa.a@kkumail.com
Requires-Dist: scikit-learn (==1.6.1)
Requires-Dist: sdv (==1.18.0)
Requires-Dist: pandas (==2.0.3)
